speaklater.py
speaklater3-1.4.dist-info/DESCRIPTION.rst
speaklater3-1.4.dist-info/METADATA
speaklater3-1.4.dist-info/RECORD
speaklater3-1.4.dist-info/WHEEL
speaklater3-1.4.dist-info/metadata.json
speaklater3-1.4.dist-info/top_level.txt
