Metadata-Version: 1.1
Name: speaklater3
Version: 1.4
Summary: Implements a lazy string for python useful for use with gettext. This version is compatible with Python 3
Home-page: https://github.com/ThomasWaldmann/speaklater
Author: Armin Ronacher, Thomas Waldmann
Author-email: armin.ronacher@active-4.com, tw@waldmann-edv.de
License: UNKNOWN
Platform: UNKNOWN
Classifier: Development Status :: 5 - Production/Stable
Classifier: License :: OSI Approved :: BSD License
Classifier: Topic :: Software Development :: Internationalization
Classifier: Programming Language :: Python
Classifier: Programming Language :: Python :: 2
Classifier: Programming Language :: Python :: 2.6
Classifier: Programming Language :: Python :: 2.7
Classifier: Programming Language :: Python :: 3
Classifier: Programming Language :: Python :: 3.3
